function_decorators/counter.py
function_decorators/logging.py
function_decorators/time.py
function_decorators-0.1.3.dist-info/LICENSE
function_decorators-0.1.3.dist-info/METADATA
function_decorators-0.1.3.dist-info/WHEEL
function_decorators-0.1.3.dist-info/RECORD
