Metadata-Version: 2.3
Name: function-decorators
Version: 0.1.3
Summary: Function wrappers for Python functions. E.g., time it function.
License: GNU 3.0
Author: Dominik Braun
Author-email: dome.braun@fau.de
Requires-Python: >=3.11,<4.0
Classifier: License :: Other/Proprietary License
Classifier: Programming Language :: Python :: 3
Classifier: Programming Language :: Python :: 3.11
Classifier: Programming Language :: Python :: 3.12
Classifier: Programming Language :: Python :: 3.13
